<?xml version="1.0" encoding="UTF-8"?>
<page xmlns="http://jboss.org/schema/seam/pages"
    xmlns:xsi="http://www.w3.org/2001/XMLSchema-instance"
    xsi:schemaLocation="http://jboss.org/schema/seam/pages http://jboss.org/schema/seam/pages-2.3.xsd"
    no-conversation-view-id="/home.xhtml" login-required="true"
    view-id="/attribute/updateAttribute.xhtml">

    <restrict>#{s:hasPermission('attribute', 'access')}</restrict>

    <param name="inum" value="#{updateAttributeAction.inum}" required="true" />

    <action execute="#{updateAttributeAction.update}" if="#{updateAttributeAction.attribute == null}" on-postback="false" />

    <rewrite pattern="/attribute/update/{inum}" />

    <navigation from-action="#{updateAttributeAction.update}">
        <rule if-outcome="success">
            <begin-conversation join="true" flush-mode="manual" />
            <render view-id="/attribute/updateAttribute.xhtml" />
        </rule>

        <rule if-outcome="no_permissions">
            <end-conversation />
            <redirect view-id="/home.xhtml">
                <message severity="ERROR">You don't have permissions to modify attribute</message>
            </redirect>
        </rule>

        <rule if-outcome="failure">
            <end-conversation />
            <redirect view-id="/attribute/attributeInventory.xhtml">
                <message severity="ERROR">Failed to find attribute</message>
            </redirect>
        </rule>
    </navigation>

    <navigation from-action="#{updateAttributeAction.save}">
        <rule if-outcome="success">
            <redirect view-id="/attribute/updateAttribute.xhtml">
                <message severity="INFO">Attribute '#{updateAttributeAction.attribute.displayName}' updated successfully</message>
            </redirect>
        </rule>

        <rule if-outcome="no_permissions">
            <end-conversation />
            <redirect view-id="/attribute/attributeInventory.xhtml">
                <message severity="ERROR">You don't have permissions to update attribute '#{updateAttributeAction.attribute.displayName}'</message>
            </redirect>
        </rule>

        <rule if-outcome="failure">
            <end-conversation />
            <redirect view-id="/attribute/attributeInventory.xhtml">
                <message severity="ERROR">Failed to update attribute</message>
            </redirect>
        </rule>
    </navigation>

    <navigation from-action="#{updateAttributeAction.cancel}">
        <end-conversation />
        <redirect view-id="/attribute/attributeInventory.xhtml">
            <message severity="INFO">Attribute '#{updateAttributeAction.attribute.displayName}' not updated</message>
        </redirect>
    </navigation>

    <navigation from-action="#{cc.attrs.deleteMethod}">
        <rule if-outcome="success">
            <end-conversation />
            <redirect view-id="/attribute/attributeInventory.xhtml">
                <message severity="INFO">Attribute '#{updateAttributeAction.attribute.displayName}' removed successfully</message>
            </redirect>
        </rule>

        <rule if-outcome="failure">
            <end-conversation />
            <redirect view-id="/attribute/attributeInventory.xhtml">
                <message severity="INFO">Failed to remove attribute '#{updateAttributeAction.attribute.displayName}'</message>
            </redirect>
        </rule>
    </navigation>

</page>
